integration_test/__init__.py
integration_test/enums.py
integration_test/integration_tests.py
integration_test/schemas/__init__.py
integration_test/schemas/v2/__init__.py
integration_test/schemas/v2/definitions.py
integration_test/schemas/v2/inbound_sms_schemas.py
integration_test/schemas/v2/notification_schemas.py
integration_test/schemas/v2/template_schemas.py
integration_test/schemas/v2/templates_schemas.py
notifications_python_client/__init__.py
notifications_python_client/authentication.py
notifications_python_client/base.py
notifications_python_client/errors.py
notifications_python_client/notifications.py
notifications_python_client/utils.py
tests/__init__.py
tests/conftest.py
utils/__init__.py
utils/make_api_call.py
suap_notifica_govbr-5.7.1.dist-info/LICENSE
suap_notifica_govbr-5.7.1.dist-info/METADATA
suap_notifica_govbr-5.7.1.dist-info/WHEEL
suap_notifica_govbr-5.7.1.dist-info/top_level.txt
suap_notifica_govbr-5.7.1.dist-info/RECORD
