Metadata-Version: 2.1
Name: suap-notifica-govbr
Version: 5.7.1
Summary: Python API client for Notifica GOV.BR.
Home-page: https://github.com/ifrn-oficial/suap-notifica-govbr
Author: IFRN
License: MIT
Keywords: gds govbr notifica
Platform: UNKNOWN
Classifier: Intended Audience :: Developers
Classifier: License :: OSI Approved :: MIT License
Classifier: Development Status :: 4 - Beta
Classifier: Programming Language :: Python :: 2
Classifier: Programming Language :: Python :: 2.7
Classifier: Programming Language :: Python :: 3
Classifier: Programming Language :: Python :: 3.4
License-File: LICENSE
Requires-Dist: requests (>=2.0.0)
Requires-Dist: PyJWT (>=1.5.1)
Requires-Dist: docopt (>=0.3.0)
Requires-Dist: monotonic (>=0.1)
Requires-Dist: future
